LICENSE
README.md
admin_data_views/__init__.py
admin_data_views/admin.py
admin_data_views/apps.py
admin_data_views/settings.py
admin_data_views/templates/admin_data_views/admin_data_item_page.html
admin_data_views/templates/admin_data_views/admin_data_table_page.html
admin_data_views/templates/admin_data_views/dict_item.html
admin_data_views/templates/admin_data_views/item.html
admin_data_views/templates/admin_data_views/list_item.html
admin_data_views/templatetags/__init__.py
admin_data_views/templatetags/admin_data_utils.py
admin_data_views/typing.py
admin_data_views/utils.py
django_admin_data_views-0.4.3.dist-info/LICENSE
django_admin_data_views-0.4.3.dist-info/METADATA
django_admin_data_views-0.4.3.dist-info/WHEEL
django_admin_data_views-0.4.3.dist-info/RECORD
